[[0, 0, 0], {"batch_size": 94, "dropout_rate": 0.16262825645796353, "lr": 5.610895482085963e-05, "num_fc_units": 12, "num_layers": 2, "weight_decay": 0.08022946252279067}, {"model_based_pick": true}]
[[0, 0, 1], {"batch_size": 67, "dropout_rate": 0.1287336840424272, "lr": 0.0055161835513258695, "num_fc_units": 74, "num_layers": 4, "weight_decay": 0.10478719309617558}, {"model_based_pick": true}]
[[0, 0, 2], {"batch_size": 15, "dropout_rate": 0.08542599339897872, "lr": 0.0010636505765817495, "num_fc_units": 15, "num_layers": 2, "weight_decay": 0.056544019200251205}, {"model_based_pick": true}]
[[0, 0, 3], {"batch_size": 20, "dropout_rate": 0.09413963583671658, "lr": 4.3498467777556235e-05, "num_fc_units": 212, "num_layers": 2, "weight_decay": 0.09237596940084933}, {"model_based_pick": true}]
[[0, 0, 4], {"batch_size": 15, "dropout_rate": 0.0854440646285532, "lr": 8.35191849327346e-06, "num_fc_units": 13, "num_layers": 2, "weight_decay": 0.0728794858270783}, {"model_based_pick": true}]
[[0, 0, 5], {"batch_size": 217, "dropout_rate": 0.4568240742737769, "lr": 0.00391525083847421, "num_fc_units": 21, "num_layers": 4, "weight_decay": 0.06951671477724454}, {"model_based_pick": true}]
[[0, 0, 6], {"batch_size": 37, "dropout_rate": 0.03324576714091837, "lr": 7.751567672757685e-06, "num_fc_units": 15, "num_layers": 5, "weight_decay": 0.17163875837336062}, {"model_based_pick": true}]
[[0, 0, 7], {"batch_size": 185, "dropout_rate": 0.15298258160377065, "lr": 0.005032583694676604, "num_fc_units": 9, "num_layers": 1, "weight_decay": 0.08387362172492882}, {"model_based_pick": true}]
[[0, 0, 8], {"batch_size": 65, "dropout_rate": 0.05629074274678075, "lr": 2.494830663941926e-06, "num_fc_units": 116, "num_layers": 5, "weight_decay": 0.10540261691623629}, {"model_based_pick": true}]
[[0, 0, 9], {"batch_size": 39, "dropout_rate": 0.2983512561448402, "lr": 1.7498962384725056e-06, "num_fc_units": 56, "num_layers": 3, "weight_decay": 0.1814187442440549}, {"model_based_pick": true}]
[[0, 0, 10], {"batch_size": 12, "dropout_rate": 0.3065482911467848, "lr": 1.6935162443054098e-05, "num_fc_units": 195, "num_layers": 2, "weight_decay": 0.16807924886255723}, {"model_based_pick": true}]
[[0, 0, 11], {"batch_size": 27, "dropout_rate": 0.1209520019910727, "lr": 9.959101917982073e-05, "num_fc_units": 21, "num_layers": 2, "weight_decay": 0.1540462719877707}, {"model_based_pick": true}]
[[0, 0, 12], {"batch_size": 57, "dropout_rate": 0.4064377959692097, "lr": 3.550412715165567e-05, "num_fc_units": 94, "num_layers": 5, "weight_decay": 0.0413350151954376}, {"model_based_pick": true}]
[[0, 0, 13], {"batch_size": 17, "dropout_rate": 0.11210573096284315, "lr": 3.32337432821763e-06, "num_fc_units": 202, "num_layers": 4, "weight_decay": 0.14491910664121174}, {"model_based_pick": true}]
[[0, 0, 14], {"batch_size": 50, "dropout_rate": 0.31597041170253265, "lr": 2.5740209778559447e-05, "num_fc_units": 65, "num_layers": 5, "weight_decay": 0.09092777421786748}, {"model_based_pick": true}]
[[0, 0, 15], {"batch_size": 9, "dropout_rate": 0.36306797879511854, "lr": 0.00018932001915326367, "num_fc_units": 131, "num_layers": 4, "weight_decay": 0.1424014229994856}, {"model_based_pick": true}]
[[0, 0, 16], {"batch_size": 101, "dropout_rate": 0.3645064952770257, "lr": 0.0053275553969333155, "num_fc_units": 29, "num_layers": 2, "weight_decay": 0.148013248924468}, {"model_based_pick": true}]
[[0, 0, 17], {"batch_size": 53, "dropout_rate": 0.4323512982692115, "lr": 0.005296646501846174, "num_fc_units": 15, "num_layers": 2, "weight_decay": 0.014747435052430239}, {"model_based_pick": true}]
[[0, 0, 18], {"batch_size": 63, "dropout_rate": 0.07878535290850663, "lr": 1.0555578498892984e-06, "num_fc_units": 211, "num_layers": 3, "weight_decay": 0.1638395322975664}, {"model_based_pick": true}]
[[0, 0, 19], {"batch_size": 87, "dropout_rate": 0.0780862073085864, "lr": 0.0010016544751575427, "num_fc_units": 140, "num_layers": 1, "weight_decay": 0.06958257697363875}, {"model_based_pick": true}]
[[0, 0, 20], {"batch_size": 74, "dropout_rate": 0.3805295919531732, "lr": 0.00047165785113484403, "num_fc_units": 34, "num_layers": 1, "weight_decay": 0.13863679038859475}, {"model_based_pick": true}]
[[0, 0, 21], {"batch_size": 110, "dropout_rate": 0.44025563069972484, "lr": 0.0007293370352477673, "num_fc_units": 16, "num_layers": 1, "weight_decay": 0.11753212929103532}, {"model_based_pick": true}]
[[0, 0, 22], {"batch_size": 27, "dropout_rate": 0.2928776773652459, "lr": 0.0024180672274440275, "num_fc_units": 141, "num_layers": 5, "weight_decay": 0.15924417803426139}, {"model_based_pick": true}]
[[0, 0, 23], {"batch_size": 132, "dropout_rate": 0.06720352723562062, "lr": 4.513303038135472e-06, "num_fc_units": 188, "num_layers": 5, "weight_decay": 0.006595581281299518}, {"model_based_pick": true}]
[[0, 0, 24], {"batch_size": 50, "dropout_rate": 0.24072268604841418, "lr": 0.00014626418757386308, "num_fc_units": 59, "num_layers": 4, "weight_decay": 0.012462360388130082}, {"model_based_pick": true}]
[[0, 0, 25], {"batch_size": 198, "dropout_rate": 0.17697322778441132, "lr": 5.63498060801522e-06, "num_fc_units": 69, "num_layers": 4, "weight_decay": 0.11699941110095}, {"model_based_pick": true}]
[[0, 0, 26], {"batch_size": 31, "dropout_rate": 0.25269938479603327, "lr": 0.0027442841468894915, "num_fc_units": 21, "num_layers": 4, "weight_decay": 0.07235424375146225}, {"model_based_pick": true}]
[[1, 0, 0], {"batch_size": 15, "dropout_rate": 0.11140350499990237, "lr": 0.0012284776388666293, "num_fc_units": 22, "num_layers": 1, "weight_decay": 0.039800286717930275}, {"model_based_pick": true}]
[[1, 0, 1], {"batch_size": 69, "dropout_rate": 0.24762176327336627, "lr": 0.008633404054954961, "num_fc_units": 235, "num_layers": 3, "weight_decay": 0.1563286938807258}, {"model_based_pick": true}]
[[1, 0, 2], {"batch_size": 245, "dropout_rate": 0.1719329503981788, "lr": 0.00027885875810926795, "num_fc_units": 21, "num_layers": 3, "weight_decay": 0.07829881065139525}, {"model_based_pick": true}]
[[1, 0, 3], {"batch_size": 197, "dropout_rate": 0.3305041165406258, "lr": 8.217947752883421e-05, "num_fc_units": 103, "num_layers": 1, "weight_decay": 0.031106454264620057}, {"model_based_pick": true}]
[[1, 0, 4], {"batch_size": 81, "dropout_rate": 0.36580990701054494, "lr": 0.00022638067113015686, "num_fc_units": 99, "num_layers": 1, "weight_decay": 0.035501319845831034}, {"model_based_pick": true}]
[[1, 0, 5], {"batch_size": 252, "dropout_rate": 0.1695302629321535, "lr": 0.006570849557048338, "num_fc_units": 27, "num_layers": 1, "weight_decay": 0.05894665810207084}, {"model_based_pick": true}]
[[1, 0, 6], {"batch_size": 8, "dropout_rate": 0.25669524077398387, "lr": 1.728652209048386e-05, "num_fc_units": 164, "num_layers": 1, "weight_decay": 0.13519635184330256}, {"model_based_pick": true}]
[[1, 0, 7], {"batch_size": 79, "dropout_rate": 0.3088685865825342, "lr": 0.007493614916853813, "num_fc_units": 26, "num_layers": 1, "weight_decay": 0.16383625112042124}, {"model_based_pick": true}]
[[1, 0, 8], {"batch_size": 76, "dropout_rate": 0.26073916505003397, "lr": 0.007768445911774983, "num_fc_units": 253, "num_layers": 2, "weight_decay": 0.1345381222096505}, {"model_based_pick": true}]
[[2, 0, 0], {"batch_size": 82, "dropout_rate": 0.08509999154935854, "lr": 0.0005688750186408731, "num_fc_units": 9, "num_layers": 3, "weight_decay": 0.09877918688333756}, {"model_based_pick": true}]
[[2, 0, 1], {"batch_size": 176, "dropout_rate": 0.07344684434469156, "lr": 6.625782989565034e-05, "num_fc_units": 14, "num_layers": 2, "weight_decay": 0.02432874936792289}, {"model_based_pick": true}]
[[2, 0, 2], {"batch_size": 32, "dropout_rate": 0.4914487388544217, "lr": 3.6559307246648506e-05, "num_fc_units": 19, "num_layers": 1, "weight_decay": 0.005299684051434259}, {"model_based_pick": true}]
[[2, 0, 3], {"batch_size": 135, "dropout_rate": 0.058651569355961386, "lr": 2.1846062576704097e-05, "num_fc_units": 50, "num_layers": 2, "weight_decay": 0.14062081219034164}, {"model_based_pick": true}]
[[2, 0, 4], {"batch_size": 102, "dropout_rate": 0.4513332104917853, "lr": 1.728897206794482e-05, "num_fc_units": 8, "num_layers": 3, "weight_decay": 0.10840109862799516}, {"model_based_pick": true}]
[[2, 0, 5], {"batch_size": 12, "dropout_rate": 0.23129210466060934, "lr": 3.881104694286812e-06, "num_fc_units": 8, "num_layers": 4, "weight_decay": 0.07681481754287973}, {"model_based_pick": true}]
[[3, 0, 0], {"batch_size": 57, "dropout_rate": 0.12009557035285157, "lr": 0.00012402132838139495, "num_fc_units": 8, "num_layers": 1, "weight_decay": 0.10790356115812492}, {"model_based_pick": true}]
[[3, 0, 1], {"batch_size": 143, "dropout_rate": 0.24941284624268883, "lr": 3.2987631187360734e-05, "num_fc_units": 248, "num_layers": 2, "weight_decay": 0.04146701102874264}, {"model_based_pick": true}]
[[3, 0, 2], {"batch_size": 17, "dropout_rate": 0.12088361669251418, "lr": 2.3741075598509175e-05, "num_fc_units": 11, "num_layers": 2, "weight_decay": 0.11413669502474653}, {"model_based_pick": true}]
[[3, 0, 3], {"batch_size": 202, "dropout_rate": 0.18034011133948735, "lr": 0.0010087440375100307, "num_fc_units": 12, "num_layers": 3, "weight_decay": 0.08149131236993234}, {"model_based_pick": true}]
